pykdm/__init__.py
pykdm/certificate.py
pykdm/cli.py
pykdm/dcp.py
pykdm/exceptions.py
pykdm/kdm.py
pykdm/project.py
pykdm-0.1.0.dist-info/WHEEL
pykdm-0.1.0.dist-info/entry_points.txt
pykdm-0.1.0.dist-info/METADATA
pykdm-0.1.0.dist-info/RECORD
