Metadata-Version: 2.4
Name: pykdm
Version: 0.1.0
Summary: Python wrapper for DCP-o-matic CLI tools (DCP creation and KDM generation)
Author: pykdm contributors
License-Expression: MIT
Requires-Dist: click>=8.0
Requires-Dist: cryptography>=42.0
Requires-Python: >=3.12
